custom_bench/__init__.py
custom_bench/benchmark_item.py
custom_bench/benchmarker.py
custom_bench/context.py
custom_bench/summarizer.py
custom_bench/templates.py
custom_bench/unit.py
custom_bench-0.11.0.dist-info/LICENSE
custom_bench-0.11.0.dist-info/METADATA
custom_bench-0.11.0.dist-info/WHEEL
custom_bench-0.11.0.dist-info/top_level.txt
custom_bench-0.11.0.dist-info/RECORD
