Metadata-Version: 2.1
Name: custom-bench
Version: 0.11.0
Summary: This is a simple benchmarking library for Python3 designed to be easy to understand and use. 
Author-email: "LJ. S.A." <lvjhn.mx@gmail.com>
License: Copyright 2022 LJ S.A.
Project-URL: Homepage, https://github.com/lvjhn/demo-package-python
Project-URL: Bug Tracker, https://github.com/lvjhn/demo-package-python/~/issues
Classifier: Programming Language :: Python :: 3
Classifier: License :: OSI Approved :: MIT License
Classifier: Operating System :: OS Independent
Requires-Python: >=3.7
License-File: LICENSE
Requires-Dist: backports.tarfile ==1.2.0
Requires-Dist: build ==1.2.1
Requires-Dist: certifi ==2024.6.2
Requires-Dist: cffi ==1.16.0
Requires-Dist: charset-normalizer ==3.3.2
Requires-Dist: cryptography ==42.0.8
Requires-Dist: docutils ==0.21.2
Requires-Dist: exceptiongroup ==1.2.1
Requires-Dist: idna ==3.7
Requires-Dist: importlib-metadata ==7.2.1
Requires-Dist: iniconfig ==2.0.0
Requires-Dist: jaraco.classes ==3.4.0
Requires-Dist: jaraco.context ==5.3.0
Requires-Dist: jaraco.functools ==4.0.1
Requires-Dist: jeepney ==0.8.0
Requires-Dist: keyring ==25.2.1
Requires-Dist: markdown-it-py ==3.0.0
Requires-Dist: mdurl ==0.1.2
Requires-Dist: more-itertools ==10.3.0
Requires-Dist: nh3 ==0.2.17
Requires-Dist: numpy ==2.0.0
Requires-Dist: packaging ==24.1
Requires-Dist: pandas ==2.2.2
Requires-Dist: patsy ==0.5.6
Requires-Dist: pkginfo ==1.11.1
Requires-Dist: pluggy ==1.5.0
Requires-Dist: pycparser ==2.22
Requires-Dist: Pygments ==2.18.0
Requires-Dist: pyproject-hooks ==1.1.0
Requires-Dist: pytest ==8.2.2
Requires-Dist: python-dateutil ==2.9.0.post0
Requires-Dist: pytz ==2024.1
Requires-Dist: readme-renderer ==43.0
Requires-Dist: requests ==2.32.3
Requires-Dist: requests-toolbelt ==1.0.0
Requires-Dist: rfc3986 ==2.0.0
Requires-Dist: rich ==13.7.1
Requires-Dist: scipy ==1.13.1
Requires-Dist: SecretStorage ==3.3.3
Requires-Dist: six ==1.16.0
Requires-Dist: statsmodels ==0.14.2
Requires-Dist: toml ==0.10.2
Requires-Dist: tomli ==2.0.1
Requires-Dist: twine ==5.1.0
Requires-Dist: tzdata ==2024.1
Requires-Dist: urllib3 ==2.2.2
Requires-Dist: zipp ==3.19.2
